README.rst
setup.py
test.py
seshet/__init__.py
seshet/bot.py
seshet/config.py
seshet/utils.py
seshet.egg-info/PKG-INFO
seshet.egg-info/SOURCES.txt
seshet.egg-info/dependency_links.txt
seshet.egg-info/requires.txt
seshet.egg-info/top_level.txt