Metadata-Version: 1.1
Name: seshet
Version: 0.1.0-2
Summary: Modular, dynamic IRC bot
Home-page: https://github.com/kopachris/seshet
Author: Christopher Koch
Author-email: ch_koch@outlook.com
License: BSD
Platform: UNKNOWN
Classifier: Development Status :: 3 - Alpha
Classifier: Operating System :: OS Independent
Classifier: License :: OSI Approved :: BSD License
Classifier: Programming Language :: Python
Classifier: Programming Language :: Python :: 3
Classifier: Programming Language :: Python :: 3.4
Classifier: Topic :: Communications :: Chat :: Internet Relay Chat
Classifier: Topic :: Software Development :: Libraries :: Application Frameworks
Classifier: Topic :: Software Development :: Libraries :: Python Modules
